christmas/__init__.py
christmas/__main__.py
christmas/support.py
christmas/tree.py
tests/__init__.py
tests/test_tree.py
christmas_tree-0.3.0.dist-info/LICENSE.md
christmas_tree-0.3.0.dist-info/METADATA
christmas_tree-0.3.0.dist-info/WHEEL
christmas_tree-0.3.0.dist-info/top_level.txt
christmas_tree-0.3.0.dist-info/RECORD
