Metadata-Version: 2.1
Name: christmas-tree
Version: 0.3.0
Summary: A simple cli christmas tree, made just for christmas mood :)
Home-page: https://github.com/vyahello/christmas-tree
Author: Volodymyr Yahello
Author-email: vyahello@gmail.com
License: UNKNOWN
Platform: UNKNOWN
Classifier: Programming Language :: Python :: 3.6
Classifier: Programming Language :: Python :: 3.7
Classifier: Programming Language :: Python :: 3.8
Classifier: License :: OSI Approved :: MIT License
Classifier: Operating System :: OS Independent
Requires-Python: >=3.6
